pytorch_grad_cam/__init__.py
pytorch_grad_cam/activations_and_gradients.py
pytorch_grad_cam/gradcam.py
pytorch_grad_cam/guided_backprop.py
pytorch_grad_cam/utils/__init__.py
pytorch_grad_cam/utils/image.py
grad_cam-1.0.0.dist-info/LICENSE
grad_cam-1.0.0.dist-info/METADATA
grad_cam-1.0.0.dist-info/WHEEL
grad_cam-1.0.0.dist-info/top_level.txt
grad_cam-1.0.0.dist-info/RECORD
