Metadata-Version: 2.1
Name: grad-cam
Version: 1.0.0
Summary: Grad-CAM visualization tool for PyTorch models.
Home-page: https://github.com/jacobgil/pytorch-grad-cam
Author: Jacob Gildenblat
Author-email: jacob.gildenblat@gmail.com
License: UNKNOWN
Project-URL: Bug Tracker, https://github.com/jacobgil/pytorch-grad-cam/issues
Platform: UNKNOWN
Classifier: Programming Language :: Python :: 3
Classifier: License :: OSI Approved :: MIT License
Classifier: Operating System :: OS Independent
Requires-Python: >=3.6
